FirebaseStream/FirebaseStream.py
FirebaseStream/__init__.py
firebase_streamer-0.0.1.dist-info/LICENSE
firebase_streamer-0.0.1.dist-info/METADATA
firebase_streamer-0.0.1.dist-info/WHEEL
firebase_streamer-0.0.1.dist-info/top_level.txt
firebase_streamer-0.0.1.dist-info/RECORD
